CHANGES.txt
bootstrap.py
buildout.cfg
setup.py
src/z3c/__init__.py
src/z3c.recipe.epydoc.egg-info/PKG-INFO
src/z3c.recipe.epydoc.egg-info/SOURCES.txt
src/z3c.recipe.epydoc.egg-info/dependency_links.txt
src/z3c.recipe.epydoc.egg-info/entry_points.txt
src/z3c.recipe.epydoc.egg-info/namespace_packages.txt
src/z3c.recipe.epydoc.egg-info/not-zip-safe
src/z3c.recipe.epydoc.egg-info/requires.txt
src/z3c.recipe.epydoc.egg-info/top_level.txt
src/z3c/recipe/__init__.py
src/z3c/recipe/epydoc/__init__.py
src/z3c/recipe/epydoc/readme.txt