Metadata-Version: 1.0
Name: z3c.recipe.epydoc
Version: 0.0.3
Summary: Use EpyDoc to build documentation for python modules
Home-page: http://pypi.python.org/pypi/z3c.recipe.epydoc/
Author: Andrew Mleczko
Author-email: andrew@mleczko.net
License: ZPL 2.1
Platform: UNKNOWN
Classifier: Development Status :: 3 - Alpha
Classifier: Framework :: Zope2
Classifier: Framework :: Zope3
Classifier: Framework :: Plone
Classifier: Natural Language :: English
Classifier: Intended Audience :: Developers
Classifier: License :: OSI Approved :: Zope Public License
Classifier: Operating System :: OS Independent
Classifier: Programming Language :: Python
